alwakeupword/AlWakeUpWord.py
alwakeupword/AlWakeUpWordDataPreparation.py
alwakeupword/AlWakeUpWordDataPreprocessing.py
alwakeupword/AlWakeUpWordPrediction.py
alwakeupword/AlWakeUpWordTrainer.py
alwakeupword/__init__.py
alwakeupword/cli.py
alwakeupword/notification.wav
alwakeupword/prediction.wav
alwakeupword/audio/0.wav
alwakeupword/audio/1.wav
alwakeupword/audio/10.wav
alwakeupword/audio/100.wav
alwakeupword/audio/101.wav
alwakeupword/audio/102.wav
alwakeupword/audio/103.wav
alwakeupword/audio/104.wav
alwakeupword/audio/105.wav
alwakeupword/audio/106.wav
alwakeupword/audio/107.wav
alwakeupword/audio/108.wav
alwakeupword/audio/109.wav
alwakeupword/audio/11.wav
alwakeupword/audio/110.wav
alwakeupword/audio/111.wav
alwakeupword/audio/112.wav
alwakeupword/audio/113.wav
alwakeupword/audio/114.wav
alwakeupword/audio/115.wav
alwakeupword/audio/116.wav
alwakeupword/audio/117.wav
alwakeupword/audio/118.wav
alwakeupword/audio/119.wav
alwakeupword/audio/12.wav
alwakeupword/audio/120.wav
alwakeupword/audio/121.wav
alwakeupword/audio/122.wav
alwakeupword/audio/123.wav
alwakeupword/audio/124.wav
alwakeupword/audio/125.wav
alwakeupword/audio/126.wav
alwakeupword/audio/127.wav
alwakeupword/audio/128.wav
alwakeupword/audio/129.wav
alwakeupword/audio/13.wav
alwakeupword/audio/130.wav
alwakeupword/audio/131.wav
alwakeupword/audio/132.wav
alwakeupword/audio/133.wav
alwakeupword/audio/134.wav
alwakeupword/audio/135.wav
alwakeupword/audio/136.wav
alwakeupword/audio/137.wav
alwakeupword/audio/138.wav
alwakeupword/audio/139.wav
alwakeupword/audio/14.wav
alwakeupword/audio/140.wav
alwakeupword/audio/141.wav
alwakeupword/audio/142.wav
alwakeupword/audio/143.wav
alwakeupword/audio/144.wav
alwakeupword/audio/145.wav
alwakeupword/audio/146.wav
alwakeupword/audio/147.wav
alwakeupword/audio/148.wav
alwakeupword/audio/149.wav
alwakeupword/audio/15.wav
alwakeupword/audio/150.wav
alwakeupword/audio/151.wav
alwakeupword/audio/152.wav
alwakeupword/audio/153.wav
alwakeupword/audio/154.wav
alwakeupword-1.0.0.dist-info/LICENSE
alwakeupword-1.0.0.dist-info/METADATA
alwakeupword-1.0.0.dist-info/WHEEL
alwakeupword-1.0.0.dist-info/entry_points.txt
alwakeupword-1.0.0.dist-info/top_level.txt
alwakeupword-1.0.0.dist-info/RECORD
