Metadata-Version: 2.1
Name: alwakeupword
Version: 1.0.0
Summary: alwakeupword explicitly request the attention of a computer using a wake up word and also allows user to make dataset and train a model of their own wake up word.
Home-page: https://github.com/alankarartist/alwakeupword
Author: Alankar Singh
Author-email: alankarartist@gmail.com
License: MIT
Platform: UNKNOWN
Classifier: License :: OSI Approved :: MIT License
Classifier: Programming Language :: Python :: 3.6
Classifier: Programming Language :: Python :: 3.7
Classifier: Programming Language :: Python :: 3.8
Classifier: Programming Language :: Python :: 3.9
Requires-Dist: librosa (==0.8.1)
Requires-Dist: numpy (==1.19.5)
Requires-Dist: pandas (==1.3.2)
Requires-Dist: scikit-learn (==1.0.2)
Requires-Dist: scipy (==1.7.3)
Requires-Dist: sounddevice (==0.4.4)
Requires-Dist: tensorflow (==2.6.0)
